[
  {
    "page": "CBT",
    "questions": [
      {
        "id": 1,
        "question": "How helpful was the CBT page?",
        "type": "options",
        "options": ["Very helpful", "Somewhat helpful", "Not helpful"],
        "image": false
      },
      {
        "id": 2,
        "question": "Please provide your feedback on the CBT page.",
        "type": "text",
        "image": true
      }
    ]
  },
  {
    "page": "Chat",
    "questions": [
      {
        "id": 3,
        "question": "Did you find the chat feature user-friendly?",
        "type": "options",
        "options": ["Yes", "No"],
        "image": false
      },
      {
        "id": 4,
        "question": "Please provide your feedback on the chat feature.",
        "type": "text",
        "image": true
      }
    ]
  },
  {
    "page": "CopingStrategies",
    "questions": [
      {
        "id": 5,
        "question": "How effective were the coping strategies?",
        "type": "options",
        "options": ["Very effective", "Somewhat effective", "Not effective"],
        "image": false
      },
      {
        "id": 6,
        "question": "Please provide your feedback on the coping strategies.",
        "type": "text",
        "image": true
      }
    ]
  },
  {
    "page": "DrawingApp",
    "questions": [
      {
        "id": 7,
        "question": "Did you enjoy using the drawing app?",
        "type": "options",
        "options": ["Yes", "No"],
        "image": false
      },
      {
        "id": 8,
        "question": "Please provide your feedback on the drawing app.",
        "type": "text",
        "image": true
      }
    ]
  },
  {
    "page": "Forum",
    "questions": [
      {
        "id": 9,
        "question": "How useful did you find the forum?",
        "type": "options",
        "options": ["Very useful", "Somewhat useful", "Not useful"],
        "image": false
      },
      {
        "id": 10,
        "question": "Please provide your feedback on the forum.",
        "type": "text",
        "image": true
      }
    ]
  },
  {
    "page": "GoalSetting",
    "questions": [
      {
        "id": 11,
        "question": "Was the goal-setting feature helpful?",
        "type": "options",
        "options": ["Yes", "No"],
        "image": false
      },
      {
        "id": 12,
        "question": "Please provide your feedback on the goal-setting feature.",
        "type": "text",
        "image": true
      }
    ]
  },
  {
    "page": "GuidedMeditation",
    "questions": [
      {
        "id": 13,
        "question": "How effective did you find the guided meditation?",
        "type": "options",
        "options": ["Very effective", "Somewhat effective", "Not effective"],
        "image": false
      },
      {
        "id": 14,
        "question": "Please provide your feedback on the guided meditation.",
        "type": "text",
        "image": true
      }
    ]
  },
  {
    "page": "Home",
    "questions": [
      {
        "id": 15,
        "question": "Was the home page user-friendly?",
        "type": "options",
        "options": ["Yes", "No"],
        "image": false
      },
      {
        "id": 16,
        "question": "Please provide your feedback on the home page.",
        "type": "text",
        "image": true
      }
    ]
  },
  {
    "page": "MemoryMatch",
    "questions": [
      {
        "id": 17,
        "question": "Did you enjoy the memory match game?",
        "type": "options",
        "options": ["Yes", "No"],
        "image": false
      },
      {
        "id": 18,
        "question": "Please provide your feedback on the memory match game.",
        "type": "text",
        "image": true
      }
    ]
  },
  {
    "page": "MoodTracker",
    "questions": [
      {
        "id": 19,
        "question": "Was the mood tracker helpful?",
        "type": "options",
        "options": ["Yes", "No"],
        "image": false
      },
      {
        "id": 20,
        "question": "Please provide your feedback on the mood tracker.",
        "type": "text",
        "image": true
      }
    ]
  },
  {
    "page": "Profile",
    "questions": [
      {
        "id": 21,
        "question": "Was the profile page easy to navigate?",
        "type": "options",
        "options": ["Yes", "No"],
        "image": false
      },
      {
        "id": 22,
        "question": "Please provide your feedback on the profile page.",
        "type": "text",
        "image": true
      }
    ]
  },
  {
    "page": "SelfAssessment",
    "questions": [
      {
        "id": 23,
        "question": "Did you find the self-assessment helpful?",
        "type": "options",
        "options": ["Yes", "No"],
        "image": false
      },
      {
        "id": 24,
        "question": "Please provide your feedback on the self-assessment.",
        "type": "text",
        "image": true
      }
    ]
  },
  {
    "page": "SupportGroups",
    "questions": [
      {
        "id": 25,
        "question": "How helpful did you find the support groups?",
        "type": "options",
        "options": ["Very helpful", "Somewhat helpful", "Not helpful"],
        "image": false
      },
      {
        "id": 26,
        "question": "Please provide your feedback on the support groups.",
        "type": "text",
        "image": true
      }
    ]
  }
]
